wyzerctl/__init__.py
wyzerctl/main.py
wyzerctl/controllers/__init__.py
wyzerctl/controllers/base.py
wyzerctl/controllers/e2e.py
wyzerctl/core/__init__.py
wyzerctl/core/exc.py
wyzerctl/core/version.py
wyzerctl/ext/__init__.py
wyzerctl/plugins/__init__.py
wyzerctl/templates/__init__.py
wyzerctl/templates/command1.jinja2
wyzerctl-0.0.1.dev20220914082427.dist-info/LICENSE.md
wyzerctl-0.0.1.dev20220914082427.dist-info/METADATA
wyzerctl-0.0.1.dev20220914082427.dist-info/WHEEL
wyzerctl-0.0.1.dev20220914082427.dist-info/entry_points.txt
wyzerctl-0.0.1.dev20220914082427.dist-info/top_level.txt
wyzerctl-0.0.1.dev20220914082427.dist-info/RECORD
