Metadata-Version: 2.1
Name: wyzerctl
Version: 0.0.1.dev20220914082427
Summary: Wyzerctl
Home-page: https://github.com/johndoe/myapp/
Author: John Doe
Author-email: john.doe@example.com
License: unlicensed
License-File: LICENSE.md
